eotorchloader/__init__.py
eotorchloader/backend/__init__.py
eotorchloader/backend/rasterio.py
eotorchloader/datamodule/__init__.py
eotorchloader/datamodule/terria.py
eotorchloader/dataset/__init__.py
eotorchloader/dataset/patch_dataset.py
eotorchloader/dataset/scene_dataset.py
eotorchloader/dataset/utils.py
eotorchloader/display/__init__.py
eotorchloader/display/matplotlib.py
eotorchloader/transform/__init__.py
eotorchloader/transform/base.py
eotorchloader/transform/display.py
eotorchloader/transform/scale.py
eotorchloader/transform/tensor.py
EOTorchLoader-0.1.0a0.dist-info/LICENSE
EOTorchLoader-0.1.0a0.dist-info/METADATA
EOTorchLoader-0.1.0a0.dist-info/WHEEL
EOTorchLoader-0.1.0a0.dist-info/top_level.txt
EOTorchLoader-0.1.0a0.dist-info/RECORD
