Metadata-Version: 2.1
Name: EOTorchLoader
Version: 0.1.0a0
Summary: Pytorch data loader for Earth observation imagery
Home-page: https://github.com/ndavid/EOTorchLoader
Author: Nicolas DAVID
Author-email: nicolas.david@ign.fr
License: "Apache-2.0"
Project-URL: Docs: pages, https://ndavid.github.io/EOTorchLoader/
Project-URL: GitHub: issues, https://github.com/ndavid/EOTorchLoader/issues
Project-URL: GitHub: repo, https://github.com/ndavid/EOTorchLoader
Keywords: ["pytorch","earth observation","remote sensing","deep learning"]
Platform: UNKNOWN
Classifier: License :: OSI Approved :: MIT License
Classifier: Operating System :: OS Independent
Classifier: Development Status :: 3 - Alpha
Classifier: Intended Audience :: Science/Research
Classifier: Intended Audience :: Developers
Classifier: Topic :: Scientific/Engineering
Classifier: Topic :: Scientific/Engineering :: Artificial Intelligence
Classifier: Topic :: Scientific/Engineering :: GIS
Classifier: Topic :: Scientific/Engineering :: Image Processing
Classifier: Programming Language :: Python :: 3
Classifier: Programming Language :: Python :: 3 :: Only
Classifier: Programming Language :: Python :: 3.8
Classifier: Programming Language :: Python :: 3.9
Classifier: Programming Language :: Python :: 3.10
Requires-Python: >=3.8
License-File: LICENSE
Requires-Dist: numpy (>=1.19)
Requires-Dist: torch (>=1.10.0)
Requires-Dist: pytorch-lightning (>=1.5.8)
Requires-Dist: matplotlib (>=3.1.3)
Requires-Dist: tqdm (>=4.40.0)
Requires-Dist: rasterio (>=1.1.5)
Requires-Dist: pandas (>=1.0.0)
Provides-Extra: dev
Requires-Dist: black (==22.1) ; extra == 'dev'
Requires-Dist: pre-commit (>=2.17) ; extra == 'dev'
Requires-Dist: nbstripout (>=0.5.0) ; extra == 'dev'
Provides-Extra: doc
Requires-Dist: sphinx (>=4.2) ; extra == 'doc'
Requires-Dist: nbsphinx (>=0.8) ; extra == 'doc'
Requires-Dist: sphinx-panels (>=0.5.0) ; extra == 'doc'
Requires-Dist: sphinx-tabs (>=3.0.0) ; extra == 'doc'
Requires-Dist: numpydoc (>=1.2) ; extra == 'doc'
Requires-Dist: pydata-sphinx-theme (>=0.8.0) ; extra == 'doc'
